mcap_protobuf/__init__.py
mcap_protobuf/decoder.py
mcap_protobuf/py.typed
mcap_protobuf/reader.py
mcap_protobuf/schema.py
mcap_protobuf/writer.py
mcap_protobuf_support-0.5.3.dist-info/METADATA
mcap_protobuf_support-0.5.3.dist-info/WHEEL
mcap_protobuf_support-0.5.3.dist-info/top_level.txt
mcap_protobuf_support-0.5.3.dist-info/RECORD
